bitbucket_mcp/__init__.py
bitbucket_mcp/__main__.py
bitbucket_mcp/client.py
bitbucket_mcp/config.py
bitbucket_mcp/memory.py
bitbucket_mcp/server.py
bitbucket_mcp/tools/__init__.py
bitbucket_mcp/tools/branches.py
bitbucket_mcp/tools/memory.py
bitbucket_mcp/tools/pull_requests.py
bitbucket_mcp/tools/repositories.py
bitbucket_mcp/tools/search.py
bitbucket_mcp/tools/users.py
bitbucket_python_mcp-0.2.2.dist-info/METADATA
bitbucket_python_mcp-0.2.2.dist-info/WHEEL
bitbucket_python_mcp-0.2.2.dist-info/entry_points.txt
bitbucket_python_mcp-0.2.2.dist-info/licenses/LICENSE
bitbucket_python_mcp-0.2.2.dist-info/RECORD
