Metadata-Version: 2.4
Name: bitbucket-python-mcp
Version: 0.2.2
Summary: A Model Context Protocol (MCP) server for BitBucket Cloud operations
Project-URL: Homepage, https://github.com/clikader/bitbucket-python-mcp
Project-URL: Repository, https://github.com/clikader/bitbucket-python-mcp
Project-URL: Issues, https://github.com/clikader/bitbucket-python-mcp/issues
Author-email: clikader <pypi@clikader.com>
License: MIT
License-File: LICENSE
Keywords: ai,bitbucket,claude,codex,mcp,model-context-protocol
Classifier: Development Status :: 4 - Beta
Classifier: Intended Audience :: Developers
Classifier: License :: OSI Approved :: MIT License
Classifier: Programming Language :: Python :: 3
Classifier: Programming Language :: Python :: 3.12
Classifier: Programming Language :: Python :: 3.13
Classifier: Topic :: Software Development :: Libraries :: Python Modules
Classifier: Topic :: Software Development :: Version Control :: Git
Requires-Python: >=3.12
Requires-Dist: atlassian-python-api>=3.41.0
Requires-Dist: mcp>=1.25.0
Requires-Dist: niquests>=3.0.0
Provides-Extra: dev
Requires-Dist: bump-my-version>=0.28.0; extra == 'dev'
Requires-Dist: pytest-asyncio>=0.23.0; extra == 'dev'
Requires-Dist: pytest>=8.0.0; extra == 'dev'
Requires-Dist: ruff>=0.4.0; extra == 'dev'
